geomprompt/__init__.py
geomprompt/ridges/__init__.py
geomprompt/ridges/io.py
geomprompt/ridges/ridge_detect.py
geomprompt/ridges/ridge_prompts.py
geomprompt/ridges/segment.py
geomprompt-0.2.5.dist-info/AUTHORS.md
geomprompt-0.2.5.dist-info/LICENSE
geomprompt-0.2.5.dist-info/METADATA
geomprompt-0.2.5.dist-info/WHEEL
geomprompt-0.2.5.dist-info/top_level.txt
geomprompt-0.2.5.dist-info/RECORD
