Metadata-Version: 2.1
Name: geomprompt
Version: 0.2.5
Summary: GeomPrompt is the default project generated by GDA Cookiecutter. GeomPrompt contains all the boilerplate you need to create a Python package according to the best-practices of Geometric Data Analytics, Inc.
Author-email: "Kenneth R. Ball (Geometric Data Analytics, Inc)" <kenneth.ball@geomdata.com>
License: AGPLv3
Project-URL: Documentation, http://rootshape.pages.geomdata.com/geomprompt
Project-URL: Source, https://gitlab.geomdata.com/rootshape/geomprompt
License-File: LICENSE
License-File: AUTHORS.md
Requires-Dist: numpy
Requires-Dist: scipy
Requires-Dist: scikit-learn
Requires-Dist: scikit-image
Requires-Dist: pillow
Requires-Dist: opencv-python
Requires-Dist: torch
Requires-Dist: torchvision
Provides-Extra: docs
Requires-Dist: jupyter; extra == "docs"
Requires-Dist: nbsphinx; extra == "docs"
Requires-Dist: sphinx; extra == "docs"
Requires-Dist: sphinx-rtd-theme; extra == "docs"
Requires-Dist: toml; extra == "docs"
Provides-Extra: notebooks
Requires-Dist: matplotlib; extra == "notebooks"
Requires-Dist: jupyter; extra == "notebooks"
Provides-Extra: ruff
Requires-Dist: ruff==0.2.2; extra == "ruff"
Provides-Extra: testing
Requires-Dist: pytest; extra == "testing"
Requires-Dist: pytest-cov; extra == "testing"
Requires-Dist: pytest-html; extra == "testing"
Requires-Dist: pytest-timeout; extra == "testing"
Requires-Dist: pytest-xdist; extra == "testing"
